mysqlog/__init__.py
mysqlog/cli.py
mysqlog/consumer.py
mysqlog/parser.py
mysqlog/producer.py
mysqlog-1.0.7.dist-info/LICENSE.txt
mysqlog-1.0.7.dist-info/METADATA
mysqlog-1.0.7.dist-info/WHEEL
mysqlog-1.0.7.dist-info/entry_points.txt
mysqlog-1.0.7.dist-info/top_level.txt
mysqlog-1.0.7.dist-info/RECORD
