Metadata-Version: 2.1
Name: mysqlog
Version: 1.0.7
Summary: MySQL Log
Home-page: https://github.com/gavin-huhz/mysql-log
Author: 
License: MIT
Keywords: python,mysql slow log
Platform: UNKNOWN
Classifier: License :: OSI Approved :: MIT License
Classifier: Programming Language :: Python
Classifier: Programming Language :: Python :: 3
Classifier: Programming Language :: Python :: 3 :: Only
Classifier: Programming Language :: Python :: 3.8
Classifier: Programming Language :: Python :: 3.9
Classifier: Programming Language :: Python :: 3.10
Requires-Python: >=3.8
License-File: LICENSE.txt
Requires-Dist: click (==8.0.3)
Requires-Dist: pymysql (==1.0.2)
Requires-Dist: typer (==0.4.0)
